dateonly_20/__init__.py
dateonly_20/dateonly_20.cp311-win_amd64.pyd
dateonly_20-0.2.1.dist-info/LICENSE
dateonly_20-0.2.1.dist-info/METADATA
dateonly_20-0.2.1.dist-info/WHEEL
dateonly_20-0.2.1.dist-info/top_level.txt
dateonly_20-0.2.1.dist-info/RECORD
