Metadata-Version: 2.1
Name: dateonly_20
Version: 0.2.1
Summary: A package for encoding, decoding, and manipulating 20th centure dates with C-level performance.
Author: Isham Mohamed
Author-email: isham.iqbal@icloud.com
Classifier: Programming Language :: Python :: 3
Classifier: License :: OSI Approved :: MIT License
Classifier: Operating System :: OS Independent
Requires-Python: >=3.9
License-File: LICENSE
